CHANGES.txt
LICENSE.txt
MANIFEST.in
README.rst
setup.py
KitchenSink.egg-info/PKG-INFO
KitchenSink.egg-info/SOURCES.txt
KitchenSink.egg-info/dependency_links.txt
KitchenSink.egg-info/pbr.json
KitchenSink.egg-info/requires.txt
KitchenSink.egg-info/top_level.txt
bin/kk
docs/FAQ.md
kitchen_sink/__init__.py
kitchen_sink/kk.py
kitchen_sink/main.py
kitchen_sink/urwidpygments.py