Metadata-Version: 1.0
Name: KitchenSink
Version: 0.0.36
Summary: a smarter pager
Home-page: http://github.com/okayzed/kk
Author: okay
Author-email: okay.zed+kk@gmail.com
License: MIT
Platform: UNKNOWN
